sdss_tree-4.1.1.data/scripts/setup_tree.py
sdss_tree-4.1.1.dist-info/licenses/LICENSE.md
tree/__init__.py
tree/changelog.py
tree/tree.py
tree/data/dr10.cfg
tree/data/dr11.cfg
tree/data/dr12.cfg
tree/data/dr13.cfg
tree/data/dr14.cfg
tree/data/dr15.cfg
tree/data/dr16.cfg
tree/data/dr17.cfg
tree/data/dr18.cfg
tree/data/dr19.cfg
tree/data/dr7.cfg
tree/data/dr8.cfg
tree/data/dr9.cfg
tree/data/ipl1.cfg
tree/data/ipl2.cfg
tree/data/ipl3.cfg
tree/data/ipl4.cfg
tree/data/sdsswork.cfg
tree/etc/tree.yml
tree/misc/__init__.py
tree/misc/docutree.py
sdss_tree-4.1.1.dist-info/METADATA
sdss_tree-4.1.1.dist-info/WHEEL
sdss_tree-4.1.1.dist-info/top_level.txt
sdss_tree-4.1.1.dist-info/RECORD
