Metadata-Version: 2.4
Name: sdss-tree
Version: 4.1.1
Summary: Control and setup of SDSS tree environment and modules
Home-page: https://github.com/sdss/tree
Author: Brian Cherinka
Author-email: bcherinka@stsci.edu
License: BSD 3-Clause License
Project-URL: Repository, https://github.com/sdss/tree
Project-URL: Documentation, https://sdss-tree.readthedocs.org
Keywords: astronomy,software
Classifier: Intended Audience :: Science/Research
Classifier: Natural Language :: English
Classifier: Operating System :: OS Independent
Classifier: Programming Language :: Python
Classifier: Programming Language :: Python :: 3.6
Classifier: Programming Language :: Python :: 3.7
Classifier: Programming Language :: Python :: 3.8
Classifier: Topic :: Documentation :: Sphinx
Classifier: Topic :: Software Development :: Libraries :: Python Modules
Requires-Python: >=3.6
License-File: LICENSE.md
Requires-Dist: pygments>=2.6
Requires-Dist: configparser>=3.5.0
Requires-Dist: sdsstools>=0.4.5
Provides-Extra: dev
Requires-Dist: Sphinx<7.3,>=7.2.0; extra == "dev"
Requires-Dist: sphinx_bootstrap_theme>=0.4.12; extra == "dev"
Requires-Dist: recommonmark>=0.6; extra == "dev"
Requires-Dist: sphinx-argparse>=0.2.5; extra == "dev"
Requires-Dist: sphinx-issues>=1.2.0; extra == "dev"
Requires-Dist: importlib_metadata>=1.6.0; extra == "dev"
Requires-Dist: jinja2<3.1; extra == "dev"
Requires-Dist: six>=1.14; extra == "dev"
Requires-Dist: ipython>=7.9.0; extra == "dev"
Requires-Dist: matplotlib>=3.1.4; extra == "dev"
Requires-Dist: flake8>=3.7.9; extra == "dev"
Requires-Dist: doc8>=0.8.0; extra == "dev"
Requires-Dist: pytest>=5.2.2; extra == "dev"
Requires-Dist: pytest-cov>=2.8.1; extra == "dev"
Requires-Dist: pytest-mock>=1.13.0; extra == "dev"
Requires-Dist: pytest-sugar>=0.9.2; extra == "dev"
Requires-Dist: isort>=4.3.21; extra == "dev"
Requires-Dist: codecov>=2.0.15; extra == "dev"
Requires-Dist: coverage[toml]>=5.0; extra == "dev"
Requires-Dist: coveralls>=1.7; extra == "dev"
Requires-Dist: ipdb>=0.12.3; extra == "dev"
Requires-Dist: sdsstools[dev]>=0.4.0; extra == "dev"
Requires-Dist: invoke>=1.3.0; extra == "dev"
Requires-Dist: twine>=3.1.4; extra == "dev"
Requires-Dist: wheel>=0.33.6; extra == "dev"
Provides-Extra: docs
Requires-Dist: Sphinx<7.3,>=7.2.0; extra == "docs"
Requires-Dist: sphinx_bootstrap_theme>=0.4.12; extra == "docs"
Requires-Dist: recommonmark>=0.6; extra == "docs"
Requires-Dist: sphinx-argparse>=0.2.5; extra == "docs"
Requires-Dist: sphinx-issues>=1.2.0; extra == "docs"
Requires-Dist: importlib_metadata>=1.6.0; extra == "docs"
Requires-Dist: jinja2<3.1; extra == "docs"
Requires-Dist: six>=1.14; extra == "docs"
Dynamic: license-file
